{
  "analysis_basis": "mockable alert channel implementation; no real external notification sent",
  "bot_name": "prev3y_crypto_paper",
  "channels": {
    "dry_run_default": true,
    "enabled": [
      "local_jsonl",
      "telegram",
      "discord"
    ],
    "external": [
      "telegram",
      "discord"
    ],
    "local_jsonl_retained": true,
    "results": [
      {
        "channel": "local_jsonl",
        "delivered_count": 1,
        "detail": "alerts JSONL written",
        "dry_run": true,
        "enabled": true,
        "endpoint": "outputs\\monitor\\prev3y_crypto\\alerts\\20260517.jsonl",
        "error_count": 0,
        "external_post_attempted": false,
        "status": "WRITTEN",
        "test_send": false
      },
      {
        "channel": "telegram",
        "delivered_count": 1,
        "detail": "would send Telegram alerts; no POST attempted",
        "dry_run": true,
        "enabled": true,
        "endpoint": "https://api.telegram.org/bot<redacted>/sendMessage",
        "error_count": 0,
        "external_post_attempted": false,
        "status": "DRY_RUN",
        "test_send": false
      },
      {
        "channel": "discord",
        "delivered_count": 1,
        "detail": "would send Discord alerts; no POST attempted",
        "dry_run": true,
        "enabled": true,
        "endpoint": "https://discord.com/api/webhooks/<redacted>",
        "error_count": 0,
        "external_post_attempted": false,
        "status": "DRY_RUN",
        "test_send": false
      }
    ],
    "test_send_requested": false
  },
  "environment": "offline_sample",
  "fail_gates": {
    "channel_dispatch_failure": false,
    "exchange_api_present": false,
    "local_jsonl_removed": false,
    "missing_outputs": false,
    "monitor_auto_restart_present": false,
    "order_submission_code_present": false,
    "real_external_post_during_validation": false,
    "secret_hardcoded": false,
    "secret_in_vcs": false,
    "secret_written_to_logs": false,
    "test_failure": false
  },
  "git_commit": "c44e12e54fde5a46ce0f0f1d53f5deabc92022f4",
  "live_trading_status": "FORBIDDEN",
  "output_paths": {
    "alerts": "outputs\\monitor\\prev3y_crypto\\alerts\\20260517.jsonl",
    "delivery_log": "outputs\\logs\\prev3y_crypto\\20260517_task005a_alert_channel.log",
    "review_numbers": "docs\\research\\review_packets\\REVIEW-005a_NUMBERS.json",
    "review_packet": "docs\\research\\review_packets\\REVIEW-005a_PACKET.md"
  },
  "paper_execution_status": "FORBIDDEN",
  "read_only_api_boundary": {
    "api_key_requested": false,
    "exchange_connection_made": false,
    "external_posts_attempted": false
  },
  "reproducibility_hash": "06a28f791dbfeb931a35dadf1eb856f92c791d0bf8648b09ba004da5b8d58817",
  "run_date": "20260517",
  "safety_scan": {
    "api_key_requested": false,
    "exchange_connection_made": false,
    "exchange_token_violations": [],
    "forbidden_token_violations": [],
    "gates": {
      "api_key_permission_violation": false,
      "exchange_api_present": false,
      "local_jsonl_removed": false,
      "monitor_auto_restart_present": false,
      "order_submission_code_present": false,
      "secret_hardcoded": false,
      "secret_in_vcs": false,
      "secret_written_to_logs": false
    },
    "live_trading_started": false,
    "paper_execution_started": false,
    "secret_ignore": {
      "errors": [],
      "required_patterns": [
        "configs/monitor_secrets.local.yaml",
        "configs/monitor_secrets.local.yml",
        "configs/monitor_secrets.yaml",
        "configs/monitor_secrets.yml"
      ],
      "status": "PASS"
    },
    "secret_literal_violations": [],
    "secret_output_violations": [],
    "status": "PASS"
  },
  "secret_handling": {
    "local_config_gitignored": true,
    "redaction_required": true,
    "secret_values_in_outputs": false,
    "sources": [
      "environment_variables",
      "configs/monitor_secrets.local.yaml"
    ]
  },
  "status": "REVIEW_READY",
  "task": "TASK-005a Real Alert Channel",
  "warning_gates": {
    "external_channels_dry_run_only": true,
    "no_example_secrets_file": false,
    "no_test_send_flag": false,
    "only_one_channel": false,
    "readme_not_updated": false
  }
}
